dishoom/__init__.py
dishoom/dishoom.py
dishoom-1.0.0.dist-info/LICENSE.txt
dishoom-1.0.0.dist-info/METADATA
dishoom-1.0.0.dist-info/WHEEL
dishoom-1.0.0.dist-info/entry_points.txt
dishoom-1.0.0.dist-info/top_level.txt
dishoom-1.0.0.dist-info/RECORD
