Metadata-Version: 2.2
Name: dishoom
Version: 1.0.0
Summary: A python based on aircrack-ng suite
Home-page: https://github.com/itsallgoodman007
Author: Goodman
Keywords: wifi,aircrack,aircrack-ng,wifi-password,aircrack-gui
Classifier: Programming Language :: Python :: 3
Classifier: License :: OSI Approved :: MIT License
Classifier: Operating System :: POSIX :: Linux
Requires-Python: >=3.6
License-File: LICENSE.txt
Requires-Dist: PyGObject
